setup.py
shinkenplugins/__init__.py
shinkenplugins.plugins.emergency_rooms_quebec.egg-info/PKG-INFO
shinkenplugins.plugins.emergency_rooms_quebec.egg-info/SOURCES.txt
shinkenplugins.plugins.emergency_rooms_quebec.egg-info/dependency_links.txt
shinkenplugins.plugins.emergency_rooms_quebec.egg-info/entry_points.txt
shinkenplugins.plugins.emergency_rooms_quebec.egg-info/namespace_packages.txt
shinkenplugins.plugins.emergency_rooms_quebec.egg-info/requires.txt
shinkenplugins.plugins.emergency_rooms_quebec.egg-info/top_level.txt
shinkenplugins/plugins/__init__.py
shinkenplugins/plugins/emergency_rooms_quebec/__init__.py
shinkenplugins/plugins/emergency_rooms_quebec/emergency_rooms_quebec.py