Metadata-Version: 1.0
Name: shinkenplugins.plugins.emergency-rooms-quebec
Version: 1.2
Summary: Checks the occupation of stretchers in various hospitals in Quebec.
Home-page: https://github.com/savoirfairelinux/sfl-shinken-plugins
Author: Grégory Starck
Author-email: gregory.starck@savoirfairelinux.com
License: GPL3+
Platform: any
